<?xml version="1.0" encoding="UTF-8"?>
<objects serializationModel="Studio.02.02.00">
	<object class="AudioFile" id="{fe2e0c06-eeab-4920-8b6e-dc26d5411361}">
		<property name="assetPath">
			<value>Ambience/amb_forest_01_LP.wav</value>
		</property>
		<property name="frequencyInKHz">
			<value>48</value>
		</property>
		<property name="channelCount">
			<value>2</value>
		</property>
		<property name="length">
			<value>72.034020833333329</value>
		</property>
		<relationship name="masterAssetFolder">
			<destination>{bee71836-49f4-4bb0-bdef-ccaeb6f1ec0d}</destination>
		</relationship>
	</object>
</objects>
